./PKG-INFO
./README.md
./pyproject.toml
./server.py
./uv.lock
./.idea/.name
./.idea/dataSources.local.xml
./.idea/dataSources.xml
./.idea/mcp-gaokao.iml
./.idea/misc.xml
./.idea/modules.xml
./.idea/vcs.xml
./.idea/workspace.xml
./.idea/dataSources/6b884d00-18f9-429d-9d3c-6cc765175aeb.xml
./.idea/dataSources/7995f782-2132-4a0a-84c1-45d6484cf5eb.xml
./.idea/dataSources/b6a00c1b-c4cc-412c-b76c-19ffe32e6769.xml
./.idea/dataSources/6b884d00-18f9-429d-9d3c-6cc765175aeb/storage_v2/_src_/schema/main.uQUzAA.meta
./.idea/dataSources/7995f782-2132-4a0a-84c1-45d6484cf5eb/storage_v2/_src_/schema/main.uQUzAA.meta
./.idea/dataSources/b6a00c1b-c4cc-412c-b76c-19ffe32e6769/storage_v2/_src_/schema/main.uQUzAA.meta
./.idea/inspectionProfiles/profiles_settings.xml
./data/crawler.py
./data/gaokao.db
mcp_gaokao_rank-0.2.dist-info/METADATA
mcp_gaokao_rank-0.2.dist-info/WHEEL
mcp_gaokao_rank-0.2.dist-info/entry_points.txt
mcp_gaokao_rank-0.2.dist-info/RECORD
